{"id":127099,"type":"ANIME","title":{"romaji":"Wu Shan Wu Xing","english":null,"native":"雾山五行"},"coverImage":{"extraLarge":"https://s4.anilist.co/file/anilistcdn/media/anime/cover/large/bx127099-15z6aQLNkzV2.png","large":"https://s4.anilist.co/file/anilistcdn/media/anime/cover/medium/bx127099-15z6aQLNkzV2.png","color":"#e49350"},"startDate":{"year":2016,"month":12,"day":31},"endDate":{"year":null,"month":null,"day":null},"bannerImage":null,"season":null,"seasonYear":null,"description":null,"format":"ONA","status":"FINISHED","episodes":1,"duration":5,"chapters":null,"volumes":null,"favourites":24,"trending":0,"genres":["Action","Adventure","Fantasy"],"isAdult":false,"averageScore":70,"popularity":2306,"trailer":null}