{"id":129679,"type":"ANIME","title":{"romaji":"Benghuai 3: Zuihou Yi Ke","english":"Honkai Impact 3rd: Final Lesson","native":"崩坏3 最后一课"},"coverImage":{"extraLarge":"https://s4.anilist.co/file/anilistcdn/media/anime/cover/large/bx129679-iyhIcwh3wlhL.png","large":"https://s4.anilist.co/file/anilistcdn/media/anime/cover/medium/bx129679-iyhIcwh3wlhL.png","color":"#fe8650"},"startDate":{"year":2018,"month":12,"day":14},"endDate":{"year":2018,"month":12,"day":14},"bannerImage":null,"season":null,"seasonYear":null,"description":null,"format":"ONA","status":"FINISHED","episodes":1,"duration":7,"chapters":null,"volumes":null,"favourites":40,"trending":0,"genres":["Action","Sci-Fi"],"isAdult":false,"averageScore":80,"popularity":722,"trailer":{"id":"8dmvNGxYPCU","site":"youtube"}}