{"id":140103,"type":"ANIME","title":{"romaji":"Benghuai 3: Reburn: II","english":"Honkai Impact 3rd - Reburn: II","native":"崩坏3 Reburn: II"},"coverImage":{"extraLarge":"https://s4.anilist.co/file/anilistcdn/media/anime/cover/large/bx140103-rSZYzc67oJ7O.png","large":"https://s4.anilist.co/file/anilistcdn/media/anime/cover/medium/bx140103-rSZYzc67oJ7O.png","color":"#5d86e4"},"startDate":{"year":2021,"month":8,"day":6},"endDate":{"year":2021,"month":8,"day":6},"bannerImage":"https://s4.anilist.co/file/anilistcdn/media/anime/banner/140103-p4mlf9ai19AH.jpg","season":null,"seasonYear":null,"description":"A world from which Honkai has disappeared.\nA journey towards the heavens.\nThe first test flight is about to begin.\n<br><br>\n(Source: Youtube Description)","format":"ONA","status":"FINISHED","episodes":1,"duration":3,"chapters":null,"volumes":null,"favourites":4,"trending":0,"genres":["Adventure","Fantasy"],"isAdult":false,"averageScore":61,"popularity":238,"trailer":{"id":"f7Y1GcPVU3U","site":"youtube"}}